jupyter_toc_generator/__init__.py
jupyter_toc_generator/main.py
jupyter_toc_generator/notebook.py
jupyter_toc_generator/util.py
jupyter_toc_generator-0.2.0.dist-info/LICENSE
jupyter_toc_generator-0.2.0.dist-info/METADATA
jupyter_toc_generator-0.2.0.dist-info/WHEEL
jupyter_toc_generator-0.2.0.dist-info/entry_points.txt
jupyter_toc_generator-0.2.0.dist-info/top_level.txt
jupyter_toc_generator-0.2.0.dist-info/RECORD
