Metadata-Version: 2.1
Name: jupyter-toc-generator
Version: 0.2.0
Summary: Generate a table of contents incl. links and anchor tags in a Jupyter Notebook.
Home-page: https://github.com/stopwhispering/jupyter-toc-generator
Author: Johannes Heller (https://github.com/stopwhispering)
License: UNKNOWN
Platform: UNKNOWN
Classifier: Programming Language :: Python :: 3
Classifier: License :: OSI Approved :: MIT License
Classifier: Operating System :: OS Independent
Requires-Python: >=3.7
License-File: LICENSE
Requires-Dist: pyperclip
